{
  "date": "2025-11-14",
  "batch_id": "batch_69a0c0d2f81c81909ceb2ac0a713382e",
  "sectors": [
    {
      "entities": [
        "China",
        "U.S.",
        "Switzerland",
        "U.K.",
        "DeepL",
        "Picsart"
      ],
      "sector": "Energy Minerals",
      "sentiment": "negative",
      "news_category": "macro",
      "extraction_status": "ok"
    },
    {
      "entities": [
        "luxury stocks"
      ],
      "sector": "Consumer Non-Durables",
      "sentiment": "positive",
      "news_category": "products",
      "extraction_status": "ok"
    },
    {
      "entities": [
        "UK government",
        "Rachel Reeves"
      ],
      "sector": "Finance",
      "sentiment": "neutral",
      "news_category": "regulation",
      "extraction_status": "ok"
    },
    {
      "entities": [
        "AI companies",
        "DeepL",
        "Picsart"
      ],
      "sector": "Technology Services",
      "sentiment": "negative",
      "news_category": "markets",
      "extraction_status": "ok"
    }
  ]
}