{
  "date": "2026-01-01",
  "batch_id": "batch_69a0c0d2f81c81909ceb2ac0a713382e",
  "sectors": [
    {
      "entities": [
        "Sen. Bernie Sanders",
        "Gov. Ron DeSantis"
      ],
      "sector": "Electronic Technology",
      "sentiment": "negative",
      "news_category": "regulation",
      "extraction_status": "ok"
    },
    {
      "entities": [
        "Warren Buffett"
      ],
      "sector": "Finance",
      "sentiment": "neutral",
      "news_category": "other",
      "extraction_status": "ok"
    },
    {
      "entities": [
        "Stellantis",
        "Ram 1500 SRT TRX"
      ],
      "sector": "Producer Manufacturing",
      "sentiment": "positive",
      "news_category": "products",
      "extraction_status": "ok"
    },
    {
      "entities": [
        "Novo Nordisk",
        "Eli Lilly"
      ],
      "sector": "Health Services",
      "sentiment": "positive",
      "news_category": "products",
      "extraction_status": "ok"
    },
    {
      "entities": [
        "Saks Group",
        "Saks Fifth Avenue"
      ],
      "sector": "Retail Trade",
      "sentiment": "negative",
      "news_category": "markets",
      "extraction_status": "ok"
    },
    {
      "entities": [
        "TSMC"
      ],
      "sector": "Electronic Technology",
      "sentiment": "neutral",
      "news_category": "markets",
      "extraction_status": "ok"
    }
  ]
}